multiples/__init__.py
multiples/is_multiple_of_five.py
multiples/is_multiple_of_two.py
tests/__init__.py
tests/test_is_multiple_of_five.py
tests/test_is_multiple_of_two.py
multiples_library-0.1.0.dist-info/METADATA
multiples_library-0.1.0.dist-info/WHEEL
multiples_library-0.1.0.dist-info/top_level.txt
multiples_library-0.1.0.dist-info/RECORD
