Metadata-Version: 2.1
Name: multiples_library
Version: 0.1.0
Summary: A library for checking multiples of 2 and 5.
Author: Your name
Author-email: your_email@example.com
Classifier: Programming Language :: Python :: 3
Classifier: License :: OSI Approved :: MIT License
Classifier: Operating System :: OS Independent
Requires-Python: >=3.6
